a_pandas_ex_read_sql/README.MD
a_pandas_ex_read_sql/__init__.py
a_pandas_ex_read_sql/requirements.txt
a_pandas_ex_read_sql/thirdparty.json
a_pandas_ex_read_sql-0.11.dist-info/LICENSE.rst
a_pandas_ex_read_sql-0.11.dist-info/METADATA
a_pandas_ex_read_sql-0.11.dist-info/WHEEL
a_pandas_ex_read_sql-0.11.dist-info/top_level.txt
a_pandas_ex_read_sql-0.11.dist-info/RECORD
