Metadata-Version: 2.1
Name: a-pandas-ex-read-sql
Version: 0.11
Summary: Convert any SQL Database to a Pandas DataFrame
Home-page: https://github.com/hansalemaos/a_pandas_ex_read_sql
Author: Johannes Fischer
Author-email: aulasparticularesdealemaosp@gmail.com
License: MIT
Keywords: sql,pandas,SQLite,mysql,DataFrame
Classifier: Development Status :: 4 - Beta
Classifier: Programming Language :: Python :: 3 :: Only
Classifier: Programming Language :: Python :: 3.10
Classifier: Topic :: Software Development :: Libraries :: Python Modules
Classifier: Topic :: Utilities
License-File: LICENSE.rst
Requires-Dist: a-pandas-ex-apply-ignore-exceptions
Requires-Dist: a-pandas-ex-less-memory-more-speed
Requires-Dist: check-if-nan
Requires-Dist: pandas
Requires-Dist: sqlparse
